ibx_sdk/__init__.py
ibx_sdk/bin/README.md
ibx_sdk/bin/__init__.py
ibx_sdk/bin/async_nios_certificate.py
ibx_sdk/bin/async_nios_csvexport.py
ibx_sdk/bin/async_nios_csvimport.py
ibx_sdk/bin/async_nios_get_file.py
ibx_sdk/bin/async_nios_get_log.py
ibx_sdk/bin/async_nios_get_supportbundle.py
ibx_sdk/bin/async_nios_grid_backup.py
ibx_sdk/bin/async_nios_grid_restore.py
ibx_sdk/bin/async_nios_restart_service.py
ibx_sdk/bin/async_nios_restart_status.py
ibx_sdk/bin/nios_certificate.py
ibx_sdk/bin/nios_csvexport.py
ibx_sdk/bin/nios_csvimport.py
ibx_sdk/bin/nios_get_file.py
ibx_sdk/bin/nios_get_log.py
ibx_sdk/bin/nios_get_supportbundle.py
ibx_sdk/bin/nios_grid_backup.py
ibx_sdk/bin/nios_grid_restore.py
ibx_sdk/bin/nios_restart_service.py
ibx_sdk/bin/nios_restart_status.py
ibx_sdk/cloud/__init__.py
ibx_sdk/cloud/exceptions.py
ibx_sdk/cloud/gift.py
ibx_sdk/logger/__init__.py
ibx_sdk/logger/ibx_logger.py
ibx_sdk/nios/__init__.py
ibx_sdk/nios/asynchronous/__init__.py
ibx_sdk/nios/asynchronous/fileop.py
ibx_sdk/nios/asynchronous/gift.py
ibx_sdk/nios/asynchronous/service.py
ibx_sdk/nios/csv/__init__.py
ibx_sdk/nios/csv/dhcp.py
ibx_sdk/nios/csv/dns.py
ibx_sdk/nios/csv/dns_records.py
ibx_sdk/nios/csv/enums.py
ibx_sdk/nios/csv/other.py
ibx_sdk/nios/csv/util.py
ibx_sdk/nios/exceptions.py
ibx_sdk/nios/fileop.py
ibx_sdk/nios/gift.py
ibx_sdk/nios/service.py
ibx_sdk/util/__init__.py
ibx_sdk/util/util.py
ibx_sdk-0.7.7.dist-info/METADATA
ibx_sdk-0.7.7.dist-info/WHEEL
ibx_sdk-0.7.7.dist-info/entry_points.txt
ibx_sdk-0.7.7.dist-info/licenses/LICENSE.md
ibx_sdk-0.7.7.dist-info/RECORD
