Metadata-Version: 2.4
Name: ibx-sdk
Version: 0.7.7
Summary: Infoblox API software development kit
License-File: LICENSE.md
Author: Michael Smith
Author-email: michaels@infoblox.com
Requires-Python: >=3.10,<4.0
Classifier: Programming Language :: Python :: 3
Classifier: Programming Language :: Python :: 3.10
Classifier: Programming Language :: Python :: 3.11
Classifier: Programming Language :: Python :: 3.12
Classifier: Programming Language :: Python :: 3.13
Classifier: Programming Language :: Python :: 3.14
Requires-Dist: appdirs (>=1.4.4,<2.0.0)
Requires-Dist: click (>=8.1.7,<9.0.0)
Requires-Dist: click-option-group (>=0.5.6,<0.6.0)
Requires-Dist: coloredlogs (>=15.0.1,<16.0.0)
Requires-Dist: dnspython (>=2.7.0,<3.0.0)
Requires-Dist: httpx (>=0.28.1,<0.29.0)
Requires-Dist: netaddr (>=1.3.0,<2.0.0)
Requires-Dist: pydantic (>=2.10.4,<3.0.0)
Requires-Dist: syslog-rfc5424-formatter (>=1.2.3,<2.0.0)
Requires-Dist: urllib3 (>=2.2.3,<3.0.0)
Project-URL: Documentation, https://infoblox-ps.github.io/ibx-sdk/
Project-URL: Repository, https://github.com/Infoblox-PS/ibx-sdk
